apixdev/__init__.py
apixdev/vars.py
apixdev/cli/__init__.py
apixdev/cli/config.py
apixdev/cli/images.py
apixdev/cli/main.py
apixdev/cli/project.py
apixdev/cli/projects.py
apixdev/cli/tools.py
apixdev/core/__init__.py
apixdev/core/common.py
apixdev/core/compose.py
apixdev/core/docker.py
apixdev/core/exceptions.py
apixdev/core/images.py
apixdev/core/odoo.py
apixdev/core/project.py
apixdev/core/projects.py
apixdev/core/settings.py
apixdev/core/tools.py
apixdev-0.3.6.dist-info/LICENSE
apixdev-0.3.6.dist-info/METADATA
apixdev-0.3.6.dist-info/WHEEL
apixdev-0.3.6.dist-info/entry_points.txt
apixdev-0.3.6.dist-info/top_level.txt
apixdev-0.3.6.dist-info/RECORD
