Metadata-Version: 2.1
Name: apixdev
Version: 0.3.6
Summary: ApiX CLI
Home-page: https://github.com/apikcloud/apix-cli
Author: Aurelien ROY
Author-email: roy.aurelien@gmail.com
License: MIT
Keywords: docker odoo development
Classifier: Development Status :: 5 - Production/Stable
Classifier: Intended Audience :: Developers
Classifier: Environment :: Console
Classifier: Topic :: Software Development :: Build Tools
Classifier: License :: OSI Approved :: MIT License
Classifier: Programming Language :: Python :: 3.8
Classifier: Programming Language :: Python :: 3.9
Classifier: Programming Language :: Python :: 3.10
Requires-Python: >=3.8
License-File: LICENSE
Requires-Dist: click (>=8.1.6)
Requires-Dist: OdooRPC (>=0.9.0)
Requires-Dist: PyYAML (>=6.0.1)
Requires-Dist: requests (>=2.28.2)
Requires-Dist: requirements-parser (>=0.5.0)
Requires-Dist: git-aggregator (>=4.0)
Requires-Dist: packaging (>=23.1)
Requires-Dist: pandas (>=2.0.0)
